claunch
