Metadata-Version: 1.0
Name: claunch
Version: 0.2
Summary: Launch process from vscode launch.json file
Home-page: http://github.com/grimpy/claunch
Author: Jo De Boeck
Author-email: deboeck.jo@gmail.com
License: UNKNOWN
Platform: UNKNOWN
